{"cameraMode":{"drawMode":0,"name":"Shaded","section":"Shading Mode"},"sceneLighting":true,"audioPlay":false,"sceneViewState":{"showFog":true,"showMaterialUpdate":false,"showSkybox":true,"showFlares":true,"showImageEffects":true,"showParticleSystems":true},"in2DMode":false,"pivot":{"x":-0.8605594635009766,"y":1.449108600616455,"z":-5.859973907470703},"rotation":{"x":-0.24057933688163758,"y":-0.42756518721580508,"z":0.11916676163673401,"w":-0.8631993532180786},"size":292.0779724121094,"orthographic":false}